setup.py
html/parser.py
micropython_html.parser.egg-info/PKG-INFO
micropython_html.parser.egg-info/SOURCES.txt
micropython_html.parser.egg-info/dependency_links.txt
micropython_html.parser.egg-info/requires.txt
micropython_html.parser.egg-info/top_level.txt