Metadata-Version: 1.0
Name: micropython-html.parser
Version: 3.3.3-1
Summary: CPython html.parser module ported to MicroPython
Home-page: https://github.com/micropython/micropython/issues/405
Author: MicroPython Developers
Author-email: micro-python@googlegroups.com
License: Python
Platform: UNKNOWN
